{
  "composer": "Harry WARREN – Mort DIXON",
  "year": "1928",
  "style": "STANDARD",
  "tempo": "FAST",
  "form": "32 A A B A",
  "time_signature": "4/4",
  "title": "NAGASAKI",
  "page": 291,
  "source": "Anthologie des grilles de jazz",
  "notation_notes": {
    "verse": "Header prints '24 VERSE'.",
    "patter": "Header prints '8 PATTER'."
  },
  "recordings": [
    "W.Lion Smith 49.68",
    "C.Basie 38- A.Copp-",
    "49- Quintete HCF56",
    "B.Goodman 47- M.Ka-",
    "min 54- D.Peter-",
    "son 54- D.Reinhardt 49",
    "D.Reinhardt 49",
    "F.Waller 29- B.Car-",
    "ter 37- A.Ammons 36",
    "C.Calloway 35- 9.Hen-",
    "O.Krupa 38- 9.Hen-",
    "derson 35"
  ],
  "sections": {
    "A": [
      {
        "bar": 1,
        "beats": {
          "1": "C",
          "3": "C#o7"
        }
      },
      {
        "bar": 2,
        "beats": {
          "1": "G7"
        }
      },
      {
        "bar": 3,
        "beats": {
          "1": "C",
          "3": "C#o7"
        }
      },
      {
        "bar": 4,
        "beats": {
          "1": "G7"
        }
      },
      {
        "bar": 5,
        "beats": {
          "1": "C",
          "3": "E7"
        }
      },
      {
        "bar": 6,
        "beats": {
          "1": "F",
          "3": "Fm"
        }
      },
      {
        "bar": 7,
        "beats": {
          "1": "C",
          "3": "G7"
        }
      },
      {
        "bar": 8,
        "beats": {
          "1": "C"
        }
      }
    ],
    "A1": [
      {
        "bar": 1,
        "beats": {
          "1": "C",
          "3": "C#o7"
        }
      },
      {
        "bar": 2,
        "beats": {
          "1": "G7"
        }
      },
      {
        "bar": 3,
        "beats": {
          "1": "C",
          "3": "C#o7"
        }
      },
      {
        "bar": 4,
        "beats": {
          "1": "G7"
        }
      },
      {
        "bar": 5,
        "beats": {
          "1": "C",
          "3": "E7"
        }
      },
      {
        "bar": 6,
        "beats": {
          "1": "F",
          "3": "Fm"
        }
      },
      {
        "bar": 7,
        "beats": {
          "1": "C",
          "3": "G7"
        }
      },
      {
        "bar": 8,
        "beats": {
          "1": "C"
        }
      }
    ],
    "B": [
      {
        "bar": 1,
        "beats": {
          "1": "F"
        }
      },
      {
        "bar": 2,
        "beats": {
          "1": "Fm"
        }
      },
      {
        "bar": 3,
        "beats": {
          "1": "C"
        }
      },
      {
        "bar": 4,
        "beats": {
          "1": "C7"
        }
      },
      {
        "bar": 5,
        "beats": {
          "1": "F"
        }
      },
      {
        "bar": 6,
        "beats": {
          "1": "Fm"
        }
      },
      {
        "bar": 7,
        "beats": {
          "1": "C",
          "3": "Am7"
        }
      },
      {
        "bar": 8,
        "beats": {
          "1": "D7",
          "3": "G7"
        }
      }
    ],
    "A2": [
      {
        "bar": 1,
        "beats": {
          "1": "C",
          "3": "C#o7"
        }
      },
      {
        "bar": 2,
        "beats": {
          "1": "G7"
        }
      },
      {
        "bar": 3,
        "beats": {
          "1": "C",
          "3": "C#o7"
        }
      },
      {
        "bar": 4,
        "beats": {
          "1": "G7"
        }
      },
      {
        "bar": 5,
        "beats": {
          "1": "C",
          "3": "E7"
        }
      },
      {
        "bar": 6,
        "beats": {
          "1": "F",
          "3": "Fm"
        }
      },
      {
        "bar": 7,
        "beats": {
          "1": "C",
          "3": "G7"
        }
      },
      {
        "bar": 8,
        "beats": {
          "1": "C"
        }
      }
    ]
  }
}