{"composer": "Sol PARKER – Henry SANICOLA", "year": "1941", "style": "STANDARD", "tempo": "MEDIUM", "form": "32 A B A C", "time_signature": "4/4", "notation_notes": {"verse": "Header prints '4 VERSE'.", "A1_arrow": "3rd printed row (A1) is a leading-arrow row copying section A positionally; dash boxes take the same-position bar from A."}, "recordings": ["T.Dorsey 41- B.Doggett 54- K.Dorham 60-", "H.Humes 50- G.Lewis 45- Montgomery Bros 61", "S.Rollins 51- C.Thornhill 41- R.Charles 52", "J.Hodges 52- S.Kenton 41- Sam Taylor 56", "C.Basie 63- El.Jones 65"], "sections": {"A": [{"bar": 1, "beats": {"1": "Dm7"}}, {"bar": 2, "beats": {"1": "G7"}}, {"bar": 3, "beats": {"1": "Cmaj7", "3": "Dm7"}}, {"bar": 4, "beats": {"1": "Em7", "3": "Eb o7"}}, {"bar": 5, "beats": {"1": "Dm7"}}, {"bar": 6, "beats": {"1": "G7", "3": "G7#5"}}, {"bar": 7, "beats": {"1": "Cmaj7"}}, {"bar": 8, "beats": {"1": "Em7", "3": "A7"}}], "B": [{"bar": 1, "beats": {"1": "Dm7"}}, {"bar": 2, "beats": {"1": "G7", "3": "G7#5"}}, {"bar": 3, "beats": {"1": "Cmaj7", "3": "(Fm7)"}}, {"bar": 4, "beats": {"1": "Em7", "3": "Am7"}}, {"bar": 5, "beats": {"1": "D7", "3": "(Eb7)"}}, {"bar": 6, "beats": {"1": "D7"}}, {"bar": 7, "beats": {"1": "G7", "3": "(F7)"}}, {"bar": 8, "beats": {"1": "Em7", "3": "A9b6"}}], "A1": [{"bar": 1, "beats": {"1": "Dm7"}}, {"bar": 2, "beats": {"1": "G7"}}, {"bar": 3, "beats": {"1": "Cmaj7", "3": "Dm7"}}, {"bar": 4, "beats": {"1": "Em7", "3": "Eb o7"}}, {"bar": 5, "beats": {"1": "Dm7"}}, {"bar": 6, "beats": {"1": "G7", "3": "G7#5"}}, {"bar": 7, "beats": {"1": "Cmaj7"}}, {"bar": 8, "beats": {"1": "Em7", "3": "A7"}}], "C": [{"bar": 1, "beats": {"1": "Dm7"}}, {"bar": 2, "beats": {"1": "Bm7b5", "3": "E7"}}, {"bar": 3, "beats": {"1": "Am", "3": "Am7"}}, {"bar": 4, "beats": {"1": "D9"}}, {"bar": 5, "beats": {"1": "C6", "3": "Em7", "4": "Eb7"}}, {"bar": 6, "beats": {"1": "Dm7", "3": "Db9"}}, {"bar": 7, "beats": {"1": "C6"}}, {"bar": 8, "beats": {"1": "C6"}}]}, "title": "THIS LOVE OF MINE", "page": 423, "source": "Anthologie des grilles de jazz"}