{"composer": "Thornton W. ALLEN – M.W. SHEAFE – C.A. ROBBINS", "year": "1910", "style": "EARLY JAZZ", "tempo": "MEDIUM FAST", "form": "32 A B A' C | 32 A B A' C", "time_signature": "4/4", "same_chord_changes": "\"Bill Bailey\" (theme 2)", "recordings": ["L.Armstrong 60- l.Ory", "Kings of Dixieland 59", "J.Marsh 65- N.Lamare 44- M.Spanier 40", "Lawson/Haggart 55- Millenderickson 31", "Bob Crosby 36- G.Krupa 40- Al Hall 57"], "variants": [{"applies_to": "Bar 42 for statement of the melody", "bars": [{"bar": 1, "beats": {"1": "Bb", "3": "G7"}}, {"bar": 2, "beats": {"1": "Cm", "3": "G7"}}, {"bar": 3, "beats": {"1": "Cm"}}]}], "sections": {"s1_A": [{"bar": 1, "beats": {"1": "Bb"}}, {"bar": 2, "beats": {"1": "Bb", "3": "Dbo7"}}, {"bar": 3, "beats": {"1": "Cm7", "3": "F7"}}, {"bar": 4, "beats": {"1": "Cm7", "3": "F7"}}, {"bar": 5, "beats": {"1": "Cm7", "3": "F7"}}, {"bar": 6, "beats": {"1": "Cm7", "3": "F7"}}, {"bar": 7, "beats": {"1": "Bb", "4": "Bo7"}}, {"bar": 8, "beats": {"1": "F7"}}], "s1_B": [{"bar": 1, "beats": {"1": "Bb"}}, {"bar": 2, "beats": {"1": "Bb", "3": "Dbo7"}}, {"bar": 3, "beats": {"1": "F"}}, {"bar": 4, "beats": {"1": "F", "3": "F#o7"}}, {"bar": 5, "beats": {"1": "C7"}}, {"bar": 6, "beats": {"1": "F7"}}, {"bar": 7, "beats": {"1": "F7"}}, {"bar": 8, "beats": {"1": "Eb", "3": "F7"}}], "s1_A1": [{"bar": 1, "beats": {"1": "Bb"}}, {"bar": 2, "beats": {"1": "Bb", "3": "Dbo7"}}, {"bar": 3, "beats": {"1": "Cm7", "3": "F7"}}, {"bar": 4, "beats": {"1": "Cm7", "3": "F7"}}, {"bar": 5, "beats": {"1": "Cm7", "3": "F7"}}, {"bar": 6, "beats": {"1": "Cm7", "3": "F7"}}, {"bar": 7, "beats": {"1": "Bb", "3": "F7"}}, {"bar": 8, "beats": {"1": "Bb"}}], "s1_C": [{"bar": 1, "beats": {"1": "G7"}}, {"bar": 2, "beats": {"1": "G7"}}, {"bar": 3, "beats": {"1": "Cm"}}, {"bar": 4, "beats": {"1": "Cm"}}, {"bar": 5, "beats": {"1": "C7"}}, {"bar": 6, "beats": {"1": "C7", "3": "G#o7"}}, {"bar": 7, "beats": {"1": "F7", "3": "Ebm6"}}, {"bar": 8, "beats": {"1": "F7"}}], "s2_A": [{"bar": 1, "beats": {"1": "Bb"}}, {"bar": 2, "beats": {"1": "Bb"}}, {"bar": 3, "beats": {"1": "Cm7", "3": "F7"}}, {"bar": 4, "beats": {"1": "Cm7", "3": "F7"}}, {"bar": 5, "beats": {"1": "Cm7", "3": "F7"}}, {"bar": 6, "beats": {"1": "Bb", "3": "Bo7"}}, {"bar": 7, "beats": {"1": "F7"}}, {"bar": 8, "beats": {"1": "F7"}}], "s2_B": [{"bar": 1, "beats": {"1": "F7"}}, {"bar": 2, "beats": {"1": "F7"}}, {"bar": 3, "beats": {"1": "F7"}}, {"bar": 4, "beats": {"1": "F7"}}, {"bar": 5, "beats": {"1": "F7", "3": "F7#5"}}, {"bar": 6, "beats": {"1": "Bb", "3": "Dbo7"}}, {"bar": 7, "beats": {"1": "F7"}}, {"bar": 8, "beats": {"1": "F7"}}], "s2_A1": [{"bar": 1, "beats": {"1": "Bb"}}, {"bar": 2, "beats": {"1": "Bb"}}, {"bar": 3, "beats": {"1": "Bb"}}, {"bar": 4, "beats": {"1": "Bb"}}, {"bar": 5, "beats": {"1": "Bb7"}}, {"bar": 6, "beats": {"1": "Eb"}}, {"bar": 7, "beats": {"1": "Eb"}}], "s2_C": [{"bar": 1, "beats": {"1": "Eb"}}, {"bar": 2, "beats": {"1": "Eo7"}}, {"bar": 3, "beats": {"1": "Bb"}}, {"bar": 4, "beats": {"1": "(G7)"}}, {"bar": 5, "beats": {"1": "C7"}}, {"bar": 6, "beats": {"1": "F7"}}, {"bar": 7, "beats": {"1": "Bb"}}, {"bar": 8, "beats": {"1": "Bb"}}]}, "notation_notes": {"structure": "Page prints two stacked grids, each labelled '32 A B A' C'; transcribed as strains s1 and s2.", "s1_A1_arrow": "s1 third row is a leading-arrow row (A') copying the s1 A row positionally; dashes are placeholders filled from the same position of A.", "s2_repeats": "s2 rows contain many dash bar-repeats filling from the preceding bar/positional copies.", "variant_bar": "Variant label reads 'VARIANT Bar 42 for statement of the melody'."}, "title": "WASHINGTON AND LEE SWING", "page": 444, "source": "Anthologie des grilles de jazz"}